Metadata-Version: 2.1
Name: smartquote
Version: 0.1.0
Summary: substitute or remove “smart” quotes
Home-page: https://github.com/kylebgorman/smartquote
Author: Kyle Gorman
Author-email: kylebgorman@gmail.com
License: Apache 2.0
Keywords: computational linguistics,natural language processing,language
Platform: UNKNOWN
Classifier: Programming Language :: Python :: 3.7
Classifier: Programming Language :: Python :: 3.8
Classifier: Programming Language :: Python :: 3.9
Classifier: Programming Language :: Python :: 3.10
Classifier: Development Status :: 3 - Alpha
Classifier: Environment :: Console
Classifier: License :: OSI Approved :: Apache Software License
Classifier: Operating System :: OS Independent
Classifier: Topic :: Text Processing :: Linguistic
Requires-Python: >=3.7
License-File: LICENSE.txt
